p_tlkc_privacy_ext/Anonymizer.py
p_tlkc_privacy_ext/ELReps.py
p_tlkc_privacy_ext/MFS.py
p_tlkc_privacy_ext/MVS.py
p_tlkc_privacy_ext/__init__.py
p_tlkc_privacy_ext/privacyPreserving.py
p_tlkc_privacy_ext/results.py
p_tlkc_privacy_ext-0.1.1.dist-info/LICENSE
p_tlkc_privacy_ext-0.1.1.dist-info/METADATA
p_tlkc_privacy_ext-0.1.1.dist-info/WHEEL
p_tlkc_privacy_ext-0.1.1.dist-info/top_level.txt
p_tlkc_privacy_ext-0.1.1.dist-info/RECORD
