Metadata-Version: 2.1
Name: p-tlkc-privacy-ext
Version: 0.1.1
Summary: TLKC-privacy model for process mining
Home-page: https://github.com/m4jidRafiei/TLKC-Privacy-Ext
Author: Majid Rafiei
Author-email: majid.rafiei@pads.rwth-aachen.de
License: UNKNOWN
Project-URL: Source, https://github.com/m4jidRafiei/TLKC-Privacy-Ext
Platform: UNKNOWN
Classifier: Programming Language :: Python :: 3
Classifier: License :: OSI Approved :: GNU General Public License v3 (GPLv3)
Classifier: Operating System :: OS Independent
Requires-Dist: pyfpgrowth (==1.0)
Requires-Dist: multiset (==2.1.1)
Requires-Dist: pm4py (==1.2.10)
Requires-Dist: numpy (>=1.18.1)
Requires-Dist: p-privacy-metadata (==0.0.4)
Requires-Dist: pandas (>=0.24.2)
Requires-Dist: mlxtend (==0.14.0)
Requires-Dist: python-dateutil (>=2.8.1)
